eqid/__init__.py
eqid-0.0.1.dist-info/LICENSE
eqid-0.0.1.dist-info/METADATA
eqid-0.0.1.dist-info/WHEEL
eqid-0.0.1.dist-info/top_level.txt
eqid-0.0.1.dist-info/RECORD
