Metadata-Version: 2.1
Name: eqid
Version: 0.0.1
Summary: Python package to retrieve the most recent earthquake information in Indonesia
Home-page: https://github.com/stevelukis/eqid/
Author: Steve Lukis
Author-email: stevelukis88@gmail.com
License: UNKNOWN
Project-URL: Blog, https://medium.com/@stevelukis
Platform: UNKNOWN
Classifier: Programming Language :: Python :: 3
Classifier: License :: OSI Approved :: GNU General Public License v3 (GPLv3)
Classifier: Operating System :: OS Independent
Requires-Python: >=3.6
License-File: LICENSE
Requires-Dist: beautifulsoup4 (==4.10.0)
Requires-Dist: requests (==2.26.0)
